python_utls/__init__.py
python_utls/utils/__init__.py
python_utls/utils/memoryit.py
python_utls/utils/misc.py
python_utls/utils/profileit.py
python_utls/utils/timeit.py
pyut-0.0.1.dist-info/DESCRIPTION.rst
pyut-0.0.1.dist-info/METADATA
pyut-0.0.1.dist-info/RECORD
pyut-0.0.1.dist-info/WHEEL
pyut-0.0.1.dist-info/metadata.json
pyut-0.0.1.dist-info/top_level.txt
